tashares/__init__.py
tashares/cfg.ini
tashares/cfg.py
tashares/stockhist.py
tashares/stockjob.py
tashares/stockmeta.py
tashares/stockta.py
tashares/tashares.py
tashares/wrapper.py
tashares/data/day_1
tashares/data/day_2
tashares/data/day_5
tashares/data/list_of_all
tashares/data/list_of_interest
tashares/data/list_of_interest_2022-02-19.csv
tashares/docs/sendemail.py
tashares/docs/snapshot.png
tashares/tests/test_tashares.py
tashares-0.1.5.dist-info/LICENSE
tashares-0.1.5.dist-info/METADATA
tashares-0.1.5.dist-info/WHEEL
tashares-0.1.5.dist-info/top_level.txt
tashares-0.1.5.dist-info/RECORD
