Metadata-Version: 2.1
Name: tashares
Version: 0.1.5
Summary: a TA model for China A-Shares
Home-page: https://github.com/joeycw/tashares
Author: joey.cw
Author-email: joey.cw@protonmail.com
License: MIT
Platform: UNKNOWN
License-File: LICENSE
Requires-Dist: yfinance (>=0.1.70)
Requires-Dist: TA-Lib
Requires-Dist: catboost
